{
    "swagger": "2.0",
    "info": {
        "description": "This is a sample swagger for Books API",
        "title": "Books Example API",
        "contact": {},
        "version": "1.0"
    },
    "paths": {
        "/books": {
            "get": {
                "security": [
                    {
                        "ApiKeyAuth": []
                    }
                ],
                "description": "get list of books",
                "consumes": [
                    "application/json"
                ],
                "produces": [
                    "application/json"
                ],
                "tags": [
                    "books"
                ],
                "summary": "get list of all books",
                "responses": {
                    "200": {
                        "description": "OK",
                        "schema": {
                            "type": "array",
                            "items": {
                                "$ref": "#/definitions/restapi.Book"
                            }
                        }
                    }
                }
            }
        }
    },
    "definitions": {
        "restapi.Book": {
            "type": "object",
            "properties": {
                "author": {
                    "type": "string"
                },
                "id": {
                    "type": "integer"
                },
                "title": {
                    "type": "string"
                }
            }
        }
    },
    "securityDefinitions": {
        "ApiKeyAuth": {
            "type": "apiKey",
            "name": "Authorization",
            "in": "header"
        }
    }
}